CHANGES.txt
LICENSE.txt
README.txt
setup.py
DiffLibrary2/__init__.py
DiffLibrary2/_keywords.py
DiffLibrary2/version.py
DiffLibrary2/test/__init__.py
DiffLibrary2/test/test_diffKeywords.py
robotframework_DiffLibrary2.egg-info/PKG-INFO
robotframework_DiffLibrary2.egg-info/SOURCES.txt
robotframework_DiffLibrary2.egg-info/dependency_links.txt
robotframework_DiffLibrary2.egg-info/requires.txt
robotframework_DiffLibrary2.egg-info/top_level.txt