Metadata-Version: 1.0
Name: robotframework-DiffLibrary2
Version: 0.0.2-dev
Summary: Robot Framework keyword library that will provide Diff capabilities
Home-page: https://code.google.com/p/robotframework-DiffLibrary2/
Author: Jules Barnes
Author-email: jules@julesbarnes.com
License: LICENSE.txt
Platform: UNKNOWN
